docmaker/__init__.py
docmaker/__main__.py
docmaker/app.py
docmaker/collectors/__init__.py
docmaker/collectors/odin_pdf_parser/__init__.py
docmaker/collectors/odin_pdf_parser/data_types.py
docmaker/collectors/odin_pdf_parser/odin_pdf_parser.py
docmaker/collectors/odin_pdf_parser/types.py
docmaker/config.py
docmaker/converters/__init__.py
docmaker/converters/cpf_converter.py
docmaker/converters/date_converter.py
docmaker/converters/float_converter.py
docmaker/converters/int_converter.py
docmaker/converters/path_converter.py
docmaker/converters/pics_analyzer.py
docmaker/converters/string_list_converter.py
docmaker/custom_types.py
docmaker/doc_handler/__init__.py
docmaker/doc_handler/docx_handler/__init__.py
docmaker/doc_handler/docx_handler/docx_handler.py
docmaker/doc_handler/docx_handler/jenv.py
docmaker/doc_handler/docx_handler/subdoc/__init__.py
docmaker/doc_handler/docx_handler/subdoc/subdoc.py
docmaker/doc_handler/docx_handler/subdoc_html/__init__.py
docmaker/doc_handler/docx_handler/subdoc_html/elment_parses/__init__.py
docmaker/doc_handler/docx_handler/subdoc_html/elment_parses/heading.py
docmaker/doc_handler/docx_handler/subdoc_html/elment_parses/image.py
docmaker/doc_handler/docx_handler/subdoc_html/elment_parses/paragraph.py
docmaker/doc_handler/docx_handler/subdoc_html/elment_parses/run.py
docmaker/doc_handler/docx_handler/subdoc_html/elment_parses/utils.py
docmaker/doc_handler/docx_handler/subdoc_html/subdoc_html.py
docmaker/doc_handler/docx_handler/word_handler.py
docmaker/doc_handler/docx_handler.py
docmaker/doc_handler/filters.py
docmaker/doc_handler/helpers_filters.py
docmaker/doc_handler/jinja_env_functions.py
docmaker/doc_handler/odt_handler/__init__.py
docmaker/doc_handler/odt_handler/globals.py
docmaker/doc_handler/odt_handler/helpers.py
docmaker/doc_handler/odt_handler/odt_handler.py
docmaker/doc_handler/odt_handler/render_info.py
docmaker/doc_handler/odt_handler/secretary/__init__.py
docmaker/doc_handler/odt_handler/secretary/secretary.py
docmaker-0.1.1.dist-info/METADATA
docmaker-0.1.1.dist-info/WHEEL
docmaker-0.1.1.dist-info/RECORD
