Metadata-Version: 2.1
Name: docmaker
Version: 0.1.1
Summary: 
Author: renatormc
Author-email: renatomartinsrmc@gmail.com
Requires-Python: >=3.11,<3.12
Classifier: Programming Language :: Python :: 3
Classifier: Programming Language :: Python :: 3.11
Requires-Dist: beautifulsoup4 (>=4.12.2,<5.0.0)
Requires-Dist: bootstrap-flask (>=2.3.2,<3.0.0)
Requires-Dist: docxtpl (>=0.16.7,<0.17.0)
Requires-Dist: flask (>=3.0.0,<4.0.0)
Requires-Dist: jinja2 (>=3.1.2,<4.0.0)
Requires-Dist: pdfminer-six (>=20221105,<20221106)
Requires-Dist: pillow (>=10.1.0,<11.0.0)
Requires-Dist: pydantic (>=2.4.2,<3.0.0)
Requires-Dist: pyside6 (>=6.6.0,<7.0.0)
Requires-Dist: python-dotenv (>=1.0.0,<2.0.0)
Requires-Dist: pywin32 (>=306,<307) ; sys_platform == "win32"
Requires-Dist: tinydb (>=4.8.0,<5.0.0)
Requires-Dist: tinydb-serialization (>=2.1.1,<3.0.0)
